ayum/translit/__init__.py
ayum/translit/translit.py
translit_ru-1.9.dist-info/METADATA
translit_ru-1.9.dist-info/WHEEL
translit_ru-1.9.dist-info/RECORD
