Metadata-Version: 2.4
Name: translit-ru
Version: 1.9
Summary: Translit russian cyrillic and slugify phrases
Project-URL: Homepage, https://github.com/ayum/ayum.translit
Project-URL: Bug Tracker, https://github.com/ayum/ayum.translit/issues
Author: ~ayum
License-Expression: MIT
Classifier: Development Status :: 5 - Production/Stable
Classifier: Environment :: Console
Classifier: Intended Audience :: Developers
Classifier: License :: OSI Approved :: MIT License
Classifier: Operating System :: OS Independent
Classifier: Programming Language :: Python :: 3
Classifier: Topic :: Software Development :: Libraries
Classifier: Topic :: Utilities
Requires-Python: >=3.10
Requires-Dist: pyicu>=2.6
